zino_argus_glue-0.3.0.dist-info/licenses/LICENSE
zinoargus/__init__.py
zinoargus/version.py
zinoargus/config/__init__.py
zinoargus/config/models.py
zino_argus_glue-0.3.0.dist-info/METADATA
zino_argus_glue-0.3.0.dist-info/WHEEL
zino_argus_glue-0.3.0.dist-info/entry_points.txt
zino_argus_glue-0.3.0.dist-info/top_level.txt
zino_argus_glue-0.3.0.dist-info/RECORD
