Metadata-Version: 2.4
Name: zino-argus-glue
Version: 0.3.0
Summary: Argus glue service for Zino
Author-email: Sikt - Norwegian Agency for Shared Services in Education and Research <kontakt@sikt.no>
Maintainer-email: Morten Brekkevold <morten.brekkevold@sikt.no>
License-Expression: Apache-2.0
Project-URL: Homepage, https://github.com/Uninett/zino-argus-glue
Project-URL: Changelog, https://github.com/Uninett/zino-argus-glue/blob/master/CHANGELOG.md
Platform: any
Classifier: Intended Audience :: Information Technology
Classifier: Intended Audience :: System Administrators
Classifier: Development Status :: 4 - Beta
Classifier: Programming Language :: Python :: 3 :: Only
Classifier: Programming Language :: Python :: 3.9
Classifier: Programming Language :: Python :: 3.10
Classifier: Programming Language :: Python :: 3.11
Classifier: Programming Language :: Python :: 3.12
Classifier: Topic :: System :: Networking :: Monitoring
Requires-Python: >=3.9
License-File: LICENSE
Requires-Dist: argus-api-client
Requires-Dist: requests
Requires-Dist: pydantic<2.11
Requires-Dist: zinolib>=1.3.4
Requires-Dist: tomli; python_version < "3.11"
Dynamic: license-file
